change_extension/__init__.py
change_extension/__main__.py
change_extension_recurse-1.0.1.dist-info/METADATA
change_extension_recurse-1.0.1.dist-info/WHEEL
change_extension_recurse-1.0.1.dist-info/entry_points.txt
change_extension_recurse-1.0.1.dist-info/top_level.txt
change_extension_recurse-1.0.1.dist-info/RECORD
