Metadata-Version: 2.4
Name: change-extension-recurse
Version: 1.0.1
Summary: A command-line tool to change file extensions recursively in a directory.
Author: Ben Bastianelli
Author-email: benbastianelli@gmail.com
Classifier: Programming Language :: Python :: 3
Classifier: Operating System :: OS Independent
Requires-Python: >=3.6
Dynamic: author
Dynamic: author-email
Dynamic: classifier
Dynamic: requires-python
Dynamic: summary
